.gitignore
requirements.txt
setup.py
agri_sense/__init__.py
agri_sense/main.py
agri_sense.egg-info/PKG-INFO
agri_sense.egg-info/SOURCES.txt
agri_sense.egg-info/dependency_links.txt
agri_sense.egg-info/requires.txt
agri_sense.egg-info/top_level.txt
agri_sense/data/FarmData.py
agri_sense/data/__init__.py
agri_sense/data/utils.py