Metadata-Version: 1.0
Name: agri-sense
Version: 1.6
Summary: A package for agricultural sensing in India
Home-page: UNKNOWN
Author: UNKNOWN
Author-email: UNKNOWN
License: UNKNOWN
Platform: UNKNOWN
